README.txt
redturtle.munin-configure.zcml
setup.py
docs/HISTORY.txt
redturtle/__init__.py
redturtle.munin.egg-info/PKG-INFO
redturtle.munin.egg-info/SOURCES.txt
redturtle.munin.egg-info/dependency_links.txt
redturtle.munin.egg-info/entry_points.txt
redturtle.munin.egg-info/namespace_packages.txt
redturtle.munin.egg-info/not-zip-safe
redturtle.munin.egg-info/requires.txt
redturtle.munin.egg-info/top_level.txt
redturtle/munin/__init__.py
redturtle/munin/configure.zcml
redturtle/munin/interfaces.py
redturtle/munin/zope2.py
redturtle/munin/browser/__init__.py
redturtle/munin/browser/configure.zcml
redturtle/munin/browser/global.py
redturtle/munin/browser/zodb_activity.py
redturtle/munin/browser/zope_cache_parameters.py
redturtle/munin/browser/zope_threads.py
redturtle/munin/plugins/zodb_activity.py
redturtle/munin/plugins/zope_cache_parameters.py
redturtle/munin/plugins/zope_threads.py