Metadata-Version: 1.0
Name: redturtle.munin
Version: 0.0.3
Summary: Munin plugins for zope/plone
Home-page: http://www.redturtle.it
Author: Andrew Mleczko
Author-email: andrew.mleczko@redturtle.it
License: GPL
Keywords: plone zope munin
Platform: UNKNOWN
Classifier: Programming Language :: Python
Classifier: Framework :: Plone
Classifier: Framework :: ZODB
Classifier: Framework :: Zope2
Classifier: Development Status :: 3 - Alpha
Classifier: Intended Audience :: Developers
Classifier: Intended Audience :: System Administrators
Classifier: Topic :: System :: Networking :: Monitoring
Classifier: Topic :: Software Development :: Libraries :: Python Modules
